verilog_mem8x8_latch/bitcell.v
/* 
Se vedlegg for kretskjema
Enkel bitcelle i SRAM modul.
WriteEnable og ReadEnable kan aldri være høy (1) samtidig. Ref modul ByteCell. */

module bitcell
    (
        input   inp,
        input   re,
        input   ren,
        input   we,
        input   wen,
        output  outp
    );

    wire Q0;
    wire Q1;
    wire Q2;



    pmos(Q0, inp, wen);
    nmos(Q0, inp, we);

    not(Q1, Q0);
    not(Q2, Q1);

    pmos(Q0, Q2, we);
    nmos(Q0, Q2, wen);

    pmos(outp, Q2, ren);
    nmos(outp, Q2, re);
endmodule

verilog_mem8x8/bytecell.v
/* 
Se vedlegg for kretskjema.
En bytecelle bestående av 8 stk bitceller med enkel logikk for kontroll av 
utgangsignalene WriteEnable og ReadEnable fra inngangsignalene sel(ect) og op(eration). .
Tar inn 8 bit inp(ut) signal og fordeler informasjonen til de tilhørende 8 bitcellene.
gir tilsvarende outp(ut) fra de 8 innbyrdes bitcellene.
Modul Bitcelle er konstruert i filen bitcelle.v
 */

`include "bitcell.v"                // include bitcell module to the script

module bytecell
    (
        input   [7:0]   inp,        // input
        input           op,         // operation, write = 1, read = 0
        input           sel,        // select. 1 if read/write operation is valid for one bytecell, else 0.
        output  [7:0]   outp        // output
    );
    wire re;                     // read enable
    wire we;                     // write enable
    wire wen;                    // write enable not
    wire ren;                    // read enable not
    wire opn;

    not(opn, op);                   // opn = ~op
    nand(wen, sel, op);               // we = sel & op
    nand(ren, sel, opn);              // re = sel & ~op
    not(we, wen);                   // wen = ~we
    not(re, ren);                   // ren = ~re

    bitcell bitcells [7:0]          // 8xbitcell
    (
        .inp(inp),
        .re(re),
        .we(we),
        .outp(outp),
        .ren(ren),
        .wen(wen)
    );
endmodule

verilog_mem8x8/bytecell_tb.v
`include "bytecell.v"                    // include the module 


// Test Benche for the ByteCell module
module bytecell_tb;
    reg     [7:0]   inp;
    reg             op;
    reg             sel;
    wire    [7:0]   outp;

    bytecell bytecell_insts 
    (
        .inp    (inp),
        .op     (op),
        .sel    (sel),
        .outp   (outp)
    );

    initial begin
        $dumpfile("bytecell_waveform.vcd");
        $dumpvars(1, bytecell_tb);

        inp = 8'b00000000;
        op = 0;
        sel = 0;

        #5 sel  <= 1;
        #5 op   <= 0;               inp <= 8'b10101010;
        #5 op   <= 1;
        #5 inp  <= 8'b11001100;
        #5 op   <= 0;               inp <= 8'b11110000;
        #5 sel  <= 0;
        #5 op   <= 1; sel <= 1;
        #5 op   <= 0;               inp <= 8'b01010101;
        #5 op   <= 1; sel <= 0;
        #5 op   <= 0;               inp <= 8'b00000000;
        #5 sel  <= 1;
        #5;
    end
endmodule

verilog_mem8x8/bytecell_waveform.vcd
$date
	Mon Oct 21 08:50:17 2024
$end
$version
	Icarus Verilog
$end
$timescale
	1s
$end
$scope module bytecell_tb $end
$var wire 8 ! outp [7:0] $end
$var reg 8 " inp [7:0] $end
$var reg 1 # op $end
$var reg 1 $ sel $end
$upscope $end
$enddefinitions $end
$comment Show the parameter values. $end
$dumpall
$end
#0
$dumpvars
0$
0#
b0 "
bz !
$end
#5
bx !
1$
#10
b10101010 "
#15
bz !
1#
#20
b11001100 "
#25
b11001100 !
b11110000 "
0#
#30
bz !
0$
#35
1$
1#
#40
b11110000 !
b1010101 "
0#
#45
bz !
0$
1#
#50
b0 "
0#
#55
b11110000 !
1$
