verilog_mem8x8/demux1to8bit.v
/* 
8 to 1 demux module
Se vedlegg for kretskjema 
*/
module demux1to8bit
    (
        input           inp,
        input   [2:0]   addr,
        output  [7:0]   outp
    );

    wire    [2:0]   not_addr;

    not(not_addr[0], addr[0]);
    not(not_addr[1], addr[1]);
    not(not_addr[2], addr[2]);

    and(outp[0],    inp,    not_addr[2],    not_addr[1],    not_addr[0]);
    and(outp[1],    inp,    not_addr[2],    not_addr[1],    addr[0]);
    and(outp[2],    inp,    not_addr[2],    addr[1],        not_addr[0]);
    and(outp[3],    inp,    not_addr[2],    addr[1],        addr[0]);
    and(outp[4],    inp,    addr[2],        not_addr[1],    not_addr[0]);
    and(outp[5],    inp,    addr[2],        not_addr[1],    addr[0]);
    and(outp[6],    inp,    addr[2],        addr[1],        not_addr[0]);
    and(outp[7],    inp,    addr[2],        addr[1],        addr[0]);

endmodule

verilog_mem8x8_m_tri_state_buffer/demux1to8bit_tb.v
`include "demux1to8bit.v"                  // include the module

// Test bench for 1 to 8 dembux
module demux1to8bit_tb;
    reg             inp;
    reg     [2:0]   addr;
    wire    [7:0]   outp;

    demux1to8bit demux1to8bit_inst1 (
        .inp    (inp),
        .addr   (addr),
        .outp   (outp)
    );

    initial begin 
        $dumpfile("demux1to8bit_wavefile.vcd");
        $dumpvars(1, demux1to8bit_tb);
        
        inp     = 1'b0;
        addr    = 3'b000;

        #5;
        #5  inp  <= 1'b1;    
        #5  addr <= 3'b001;
        #5  addr <= 3'b010;
        #5  addr <= 3'b011;
        #5  addr <= 3'b100;
        #5  addr <= 3'b101;
        #5  addr <= 3'b110;
        #5  addr <= 3'b111;
        #5  inp  <= 1'b0;
        #5;
    end
endmodule

verilog_mem8x8/demux1to8bit_wavefile.vcd
$date
	Tue Oct 15 15:29:48 2024
$end
$version
	Icarus Verilog
$end
$timescale
	1s
$end
$scope module demux1to8bit_tb $end
$var wire 8 ! outp [7:0] $end
$var reg 3 " addr [2:0] $end
$var reg 1 # inp $end
$upscope $end
$enddefinitions $end
#0
$dumpvars
0#
b0 "
b0 !
$end
#10
b1 !
1#
#15
b10 !
b1 "
#20
b100 !
b10 "
#25
b1000 !
b11 "
#30
b10000 !
b100 "
#35
b100000 !
b101 "
#40
b1000000 !
b110 "
#45
b10000000 !
b111 "
#50
b0 !
0#
