verilog_mem8x8_m_tri_state_buffer/flipflop.v
module flipflop
    (
        input   inp,
        input   clk,
        output  outp
    );

    wire P0;
    wire P1;
    wire inpn;
    wire outpn;
    wire clkN;
    wire clkPE;

    not(clkN, clk);
    and(clkPE, clk, clkN);

    not(inpn, inp);
    nand(P0, inp, clkPE);
    nand(P1, inpn, clkPE);
    nand(outp, P0, outpn);
    nand(outpn, P1, outp);
endmodule

verilog_mem8x8/flipflop_tb.v
`include "flipflop.v"

module flipflop_tb;
    reg inp;
    reg clkPE;
    wire outp;

    flipflop ff1 (
        .inp(inp),
        .clkPE(clkPE),
        .outp(outp)
    );

    always begin
        #9 clkPE = 1;
        #1 clkPE = 0;
    end

    initial begin
        $dumpfile("flipflop_waveform.vcd");
        $dumpvars(1, flipflop_tb);

        inp = 0;
        clkPE = 0;
                
        #5 inp <= 1; 
        #10 inp <= 0; 
        #10 inp <= 1; 
        #10 inp <= 0;
        #100 $finish;
    end
endmodule

verilog_mem8x8/flipflop_waveform.vcd
$date
	Mon Oct 21 13:46:30 2024
$end
$version
	Icarus Verilog
$end
$timescale
	1s
$end
$scope module flipflop_tb $end
$var wire 1 ! outp $end
$var reg 1 " clkPE $end
$var reg 1 # inp $end
$upscope $end
$enddefinitions $end
$comment Show the parameter values. $end
$dumpall
$end
#0
$dumpvars
0#
0"
x!
$end
#5
1#
#9
1!
1"
#10
0"
#15
0#
#19
0!
1"
#20
0"
#25
1#
#29
1!
1"
#30
0"
#35
0#
#39
0!
1"
