verilog_mem8x8/dff.v

module dff
    (
        input data,
        input we,
        output Q,
        output Qn
    );

    wire Q1;
    wire Qn1;

    nand(Q1, we, data);
    nand(Qn1, we, ~data);
    nand(Q, Q1, Qn);
    nand(Qn, Qn1, Q);
endmodule

module tb_dff;
    reg data;
    reg we;
    wire Q;
    wire Qn;

    dff dff_inst1(
        .data(data),
        .we(we),
        .Q(Q),
        .Qn(Qn)
    );

    initial begin
        $dumpfile("waveform.vcd");
        $dumpvars(1, tb_dff);

        data = 0;
        we = 0;

        #10 data <= 1;
        #10 data <= 0;
        #10 we <= 1;
        #10 we <= 0;
        #10 data <= 1; we <= 1;
        #10 we <= 0;
        #10 data <= 0;
        #10 we <= 1;
        #10 we <= 0;
        #10;
    end
endmodule

verilog_mem8x8/bytecell.v
module bytecell
    (
        input [7:0] inp,
        input rw,
        input sel,
        output [7:0] outp
    );

    bitcell bitcells [7:0] 
    (
        .inp(inp),
        .rw(rw),
        .sel(sel),
        .outp(outp)
    );
endmodule

module tb_bytecell;
    reg [7:0] inp;
    reg rw;
    reg sel;
    wire [7:0] outp;

    bytecell uut 
    (
        .inp(inp),
        .rw(rw),
        .sel(sel),
        .outp(outp)
    );

    initial begin
        $dumpfile("waveform.vcd");
        $dumpvars(1, tb_bytecell);

        inp = 8'b00000000;
        rw = 0;
        sel = 0;

        #10 sel <= 1;
        #10 rw <= 0; inp <= 8'b10101010;
        #10 rw <= 1;
        #10 inp <= 8'b11001100;
        #10 rw <= 0; inp <= 8'b11110000;
        #10;
    end
endmodule

verilog_mem8x8/demux1to8bit.v
module demux1to8bit
    (
        input inp,
        input [2:0] addr,
        output [7:0] outp
    );

    wire not_addr[2:0];
    not(not_addr[0], addr[0]);
    not(not_addr[1], addr[1]);
    not(not_addr[2], addr[2]);

    and(outp[0], inp, not_addr[0], not_addr[1], not_addr[2]);
    and(outp[1], inp, not_addr[0], not_addr[1], addr[2]);
    and(outp[2], inp, not_addr[0], addr[1], not_addr[2]);
    and(outp[3], inp, not_addr[0], addr[1], addr[2]);
    and(outp[4], inp, addr[0], not_addr[1], not_addr[2]);
    and(outp[5], inp, addr[0], not_addr[1], addr[2]);
    and(outp[6], inp, addr[0], addr[1], not_addr[2]);
    and(outp[7], inp, addr[0], addr[1], addr[2]);
endmodule

verilog_mem8x8/ram.v
module ram
    (
        input [7:0] inp,
        input [2:0] addr,
        input op,
        input sel,
        output [7:0] outp
    );

    wire [7:0] outp_demux;

    demux1to8bit demux1to8bit_inst1
    (
        .inp(sel),
        .addr(addr),
        .outp(outp_demux)
    );

    genvar i; generate
        for (i = 0; i < 8; i = i + 1) begin : bytecell_insts1
            bytecell bytecell_inst (
                .inp(inp),
                .rw(op),
                .sel(outp_demux[i]),
                .outp(outp)
            );
        end
    endgenerate

endmodule

module tb_ram;
    reg [7:0] inp;
    reg [2:0] addr;
    reg op;
    reg sel;
    wire [7:0] outp;

    ram ram_inst (
        .inp(inp),
        .addr(addr),
        .op(op),
        .sel(sel),
        .outp(outp)
    );

    initial begin
        $dumpfile("waveform.vcd");
        $dumpvars(1, tb_ram);

        inp = 8'b00000000;
        addr = 3'b000;
        op = 1'b0;
        sel = 1'b0;

        #10 sel <= 1'b1; op <= 1'b1; inp <= 8'b10101010; addr <= 3'b001; // write AA to address 1
        #10 sel <= 1'b0;
        #10 sel <= 1'b1; op <= 1'b0; addr <= 3'b001; // read from address 1
        #10 sel <= 1'b0;
        #10 sel <= 1'b1; op <= 1'b0; addr <= 3'b010; // read from address 2
        #10 op <= 1'b1; inp <= 8'b10101011; // write AB to address 2
        #10 op <= 1'b0;
        #10;

    end
endmodule

verilog_mem8x8/bitcell.v
module bitcell
    (
        input inp,
        input rw,
        input sel,
        output outp
    );

    wire pre_outp;
    wire we;
    wire re;

    dff dff_inst1
    (
        .data(inp),
        .we(we),
        .Q(pre_outp),
        .Qn()
    );

    nmos(outp, pre_outp, re);
    and(we, rw, sel);
    and(re, ~rw, sel);
endmodule

module tb_bitcell;
    reg inp;
    reg rw;
    reg sel;
    wire outp;

    bitcell bitcell_inst1
    (
        .inp(inp),
        .sel(sel),
        .rw(rw),
        .outp(outp)
    );

    initial begin
        $dumpfile("waveform.vcd");
        $dumpvars(1, tb_bitcell);

        inp = 0;
        rw = 0;
        sel = 0;

        #10 rw <= 1;
        #10 rw <= 0;
        #10 inp <= 1; rw <= 1;
        #10 sel <= 1;
        #10 rw <= 0;
        #10 sel <= 0;
        #10 rw <= 1;
        #10 rw <= 0;
        #10;
    end
endmodule

verilog_mem8x8/waveform.vcd
$date
	Mon Oct 14 13:56:37 2024
$end
$version
	Icarus Verilog
$end
$timescale
	1s
$end
$scope module tb_bitcell $end
$var wire 1 ! outp $end
$var reg 1 " inp $end
$var reg 1 # rw $end
$var reg 1 $ sel $end
$upscope $end
$scope module tb_bytecell $end
$var wire 8 % outp [7:0] $end
$var reg 8 & inp [7:0] $end
$var reg 1 ' rw $end
$var reg 1 ( sel $end
$upscope $end
$scope module tb_dff $end
$var wire 1 ) Qn $end
$var wire 1 * Q $end
$var reg 1 + data $end
$var reg 1 , we $end
$upscope $end
$scope module tb_ram $end
$var wire 8 - outp [7:0] $end
$var reg 3 . addr [2:0] $end
$var reg 8 / inp [7:0] $end
$var reg 1 0 op $end
$var reg 1 1 sel $end
$upscope $end
$enddefinitions $end
$comment Show the parameter values. $end
$dumpall
$end
#0
$dumpvars
01
00
b0 /
b0 .
bz -
0,
0+
x*
x)
0(
0'
b0 &
bz %
0$
0#
0"
z!
$end
#10
bx %
1+
1(
1#
b1 .
b10101010 /
10
11
#20
0+
b10101010 &
0#
01
#30
0*
1)
bz %
1,
1'
1#
1"
b10101010 -
00
11
#40
z!
0,
b11001100 &
1$
bz -
01
#50
0)
1*
b11001100 %
1!
1,
1+
b11110000 &
0'
0#
bx -
b10 .
11
#60
z!
0,
0$
bz -
b10101011 /
10
#70
0+
1#
b10101011 -
00
#80
0*
1)
1,
0#
#90
0,
