verilog_mem8x8_m_tri_state_buffer/bitcell.v
/* 
Se vedlegg for kretskjema
Enkel bitcelle i SRAM modul.
WriteEnable og ReadEnable kan aldri være høy (1) samtidig. Ref modul ByteCell. */

module bitcell
    (
        input   inp,
        input   inpn,
        input   we,
        input   re,
        input   ren,
        output  outp
    );

    wire Q0;
    wire Q0n;
    wire Q1;
    wire Q1n;
    wire T0;
    wire T1;

    // supply rails. Logical 1
    supply1 VDD;
    supply0 GND;

    // D-latch
    nand(Q0, inp, we);
    nand(Q0n, inpn, we);
    nand(Q1, Q0, Q1n);
    nand(Q1n, Q0n, Q1);

    // Tri-state buffer
    pmos(T0, VDD, Q1n);
    nmos(T1, GND, Q1n);
    pmos(outp, T0, ren);
    nmos(outp, T1, re);
endmodule

verilog_mem8x8_m_tri_state_buffer/bitcell_tb.v
`include "bitcell.v"        // include the module

module bitcell_tb;
    reg     inp;
    reg     inpn;
    reg     re;
    reg     ren;
    reg     we;
    wire    outp;

    bitcell bitcell_inst1
    (
        .inp    (inp),
        .inpn   (inpn),
        .we     (we),
        .re     (re),
        .ren    (ren),
        .outp   (outp)
    );

    initial begin
        $dumpfile("bitcell_waveform.vcd");
        $dumpvars(1, bitcell_tb);

        inp     = 0;
        inpn    = 1;
        re      = 0;
        ren     = 1;
        we      = 0;

        #5 re  <= 1; ren <= 0;
        #5 re  <= 0; ren <= 1;
        #5 inp <= 1; inpn <= 0; we <= 1; 
        #5 we  <= 0; 
        #5 inp <= 0; inpn <= 1;
        #5 re  <= 1; ren <= 0;
        #5 re  <= 0; ren <= 1; we <= 1; 
        #5 we  <= 0; 
        #5 re  <= 1; ren <= 0;
        #5 re  <= 0; ren <= 1;
        #5;
    end
endmodule

verilog_mem8x8_m_tri_state_buffer/bitcell_waveform.vcd
$date
	Wed Oct 23 15:46:28 2024
$end
$version
	Icarus Verilog
$end
$timescale
	1s
$end
$scope module bitcell_tb $end
$var wire 1 ! outp $end
$var reg 1 " inp $end
$var reg 1 # inpn $end
$var reg 1 $ re $end
$var reg 1 % ren $end
$var reg 1 & we $end
$upscope $end
$enddefinitions $end
#0
$dumpvars
0&
1%
0$
1#
0"
z!
$end
#5
0%
x!
1$
#10
1%
z!
0$
#15
1&
0#
1"
#20
0&
#25
1#
0"
#30
1!
0%
1$
#35
1&
z!
1%
0$
#40
0&
#45
0%
0!
1$
#50
1%
z!
0$
