verilog_mem8x8_m_tri_state_buffer/bitcell.v
/* 
Se vedlegg for kretskjema
Enkel bitcelle i SRAM modul.
WriteEnable og ReadEnable kan aldri være høy (1) samtidig. Ref modul ByteCell. */

module bitcell
    (
        input   inp,
        input   inpn,
        input   we,
        input   re,
        input   ren,
        output  outp
    );

    wire Q0;
    wire Q0n;
    wire Q1;
    wire Q1n;
    wire T0;
    wire T1;

    // supply rails. Logical 1
    supply1 VDD;
    supply0 GND;

    // D-latch
    nand(Q0, inp, we);
    nand(Q0n, inpn, we);
    nand(Q1, Q0, Q1n);
    nand(Q1n, Q0n, Q1);

    // Tri-state buffer
    pmos(T0, VDD, Q1n);
    nmos(T1, GND, Q1n);
    pmos(outp, T0, ren);
    nmos(outp, T1, re);
endmodule

verilog_mem8x8_m_tri_state_buffer/bytecell.v
/* 
Se vedlegg for kretskjema.
En bytecelle bestående av 8 stk bitceller med enkel logikk for kontroll av 
utgangsignalene WriteEnable og ReadEnable fra inngangsignalene sel(ect) og op(eration). .
Tar inn 8 bit inp(ut) signal og fordeler informasjonen til de tilhørende 8 bitcellene.
gir tilsvarende outp(ut) fra de 8 innbyrdes bitcellene.
Modul Bitcelle er konstruert i filen bitcelle.v
 */

`include "bitcell.v"                // include bitcell module to the script

module bytecell
    (
        input   [7:0]   inp,        // input
        input   [7:0]   inpn,       // input not
        input           op,         // operation, write = 1, read = 0
        input           sel,        // select. 1 if read/write operation is valid for one bytecell, else 0.
        output  [7:0]   outp        // output
    );

    wire re;                     // read enable
    wire ren;                    // read enable not
    wire we;                     // write enable
    wire opn;

    // F Block. Se vedlegg for kretskjema
    not(opn, op);                   // opn = ~op
    and(we, sel, op);               // we = sel & op
    nand(ren, sel, opn);            // ren = sel & ~op
    not(re, ren);                   // re = ~ren

    // 8 stk bitceller
    genvar i;   generate
        for(i = 0; i < 8; i = i + 1) begin : bitcell_insts_i
            bitcell bitcells
            (
                .inp    (inp[i]),
                .inpn   (inpn[i]),
                .we     (we),
                .re     (re),
                .ren    (ren),
                .outp   (outp[i])
            );
        end
    endgenerate
endmodule

verilog_mem8x8_m_tri_state_buffer/bytecell_tb.v
`include "bytecell.v"                    // include the module 


// Test Benche for the ByteCell module
module bytecell_tb;
    reg     [7:0]   inp;
    reg     [7:0]   inpn;
    reg             op;
    reg             sel;
    wire    [7:0]   outp;

    bytecell bytecell_insts1 
    (
        .inp    (inp),
        .inpn   (inpn),
        .op     (op), 
        .sel    (sel),
        .outp   (outp)
    );

    initial begin
        $dumpfile("bytecell_waveform.vcd");
        $dumpvars(1, bytecell_tb);

        inp = 8'b00000000;
        inpn = 8'b11111111;
        op = 0;
        sel = 0;

        #5 sel  <= 1;
        #5 op   <= 0;               inp <= 8'b10101010; inpn <= 8'b01010101;
        #5 op   <= 1;
        #5 inp  <= 8'b11001100;     inpn <= 8'b00110011;
        #5 op   <= 0;               inp <= 8'b11110000; inpn <= 8'b00001111;
        #5 sel  <= 0;
        #5 op   <= 1; sel <= 1;
        #5 op   <= 0;               inp <= 8'b01010101; inpn <= 8'b10101010;
        #5 op   <= 1; sel <= 0;
        #5 op   <= 0;               inp <= 8'b00000000; inpn <= 8'b11111111;
        #5 sel  <= 1;
        #5;
    end
endmodule

verilog_mem8x8_m_tri_state_buffer/bytecell_waveform.vcd
$date
	Wed Oct 23 15:55:40 2024
$end
$version
	Icarus Verilog
$end
$timescale
	1s
$end
$scope module bytecell_tb $end
$var wire 8 ! outp [7:0] $end
$var reg 8 " inp [7:0] $end
$var reg 8 # inpn [7:0] $end
$var reg 1 $ op $end
$var reg 1 % sel $end
$upscope $end
$enddefinitions $end
#0
$dumpvars
0%
0$
b11111111 #
b0 "
bz !
$end
#5
bx !
1%
#10
b1010101 #
b10101010 "
#15
bz !
1$
#20
b110011 #
b11001100 "
#25
b11001100 !
b1111 #
b11110000 "
0$
#30
bz !
0%
#35
1%
1$
#40
b11110000 !
b10101010 #
b1010101 "
0$
#45
bz !
0%
1$
#50
b11111111 #
b0 "
0$
#55
b11110000 !
1%
