verilog_mem8x8_m_tri_state_buffer/flipflop.v
module flipflop
    (
        input   inp,
        input   clk,
        output  outp
    );

    wire P0;
    wire P1;
    wire inpn;
    wire outpn;
    wire clkN;
    wire clkPE;

    not(clkN, clk);
    and(clkPE, clk, clkN);

    not(inpn, inp);
    nand(P0, inp, clkPE);
    nand(P1, inpn, clkPE);
    nand(outp, P0, outpn);
    nand(outpn, P1, outp);
endmodule

verilog_mem8x8_m_tri_state_buffer/FSM.v
`include "flipflop.v"

module fsm
    (
        input op,
        input sel,
        input clk,
        output valid,
        output rw
    );

    wire P0;
    wire P1;
    wire P2;
    wire P3;
    wire P4;
    
    and(P0, op, sel);
    or(P3, P0, P1);
    not(P1, P2);
    nand(P2, valid, rw);
    and(P4, P2, sel);

    flipflop ff1 (
        .inp(P3),
        .clk(clk),
        .outp(rw)
    );

    flipflop ff2 (
        .inp(P4),
        .clk(clk),
        .outp(valid)
    );
endmodule

verilog_mem8x8_m_tri_state_buffer/FSM_tb.v
`include "FSM.v"

module FSM_tb;
    reg clk;
    reg op;
    reg sel;
    wire valid;
    wire rw;

    fsm fsm1 (
        .op(op),
        .sel(sel),
        .clk(clk),
        .valid(valid),
        .rw(rw)
    );

    always begin
        #5 clk = 1;
        #5 clk = 0;
    end

    initial begin
        $dumpfile("FSM_waveform.vcd");
        $dumpvars(1, FSM_tb);

        clk = 0;
        op  = 0;
        sel = 0;

        #10 op <= 0; sel <= 1; // read, valid = 1, rw = 0
        #20;
        #10 op <= 1; sel <= 1; // write, valid = 1, rw = 1
        #20; // occilate between write and stable
        #10 op <= 0; sel <= 0;
        
        #100 $finish;
    end
endmodule

verilog_mem8x8_m_tri_state_buffer/FSM_waveform.vcd
$date
	Mon Oct 28 13:57:58 2024
$end
$version
	Icarus Verilog
$end
$timescale
	1s
$end
$scope module FSM_tb $end
$var wire 1 ! valid $end
$var wire 1 " rw $end
$var reg 1 # clk $end
$var reg 1 $ op $end
$var reg 1 % sel $end
$upscope $end
$enddefinitions $end
$comment Show the parameter values. $end
$dumpall
$end
#0
$dumpvars
0%
0$
0#
x"
x!
$end
#5
0"
1#
#10
1%
0#
#15
0!
1"
1#
#20
0#
#25
1#
#30
0#
#35
1#
#40
1$
0#
#45
1!
1#
#50
0#
#55
0"
1#
#60
0#
#65
1"
1#
#70
0%
0$
0#
#75
0"
1#
#80
0#
#85
0!
1#
