verilog_mem8x8_m_tri_state_buffer/bitcell.v
/* 
Se vedlegg for kretskjema
Enkel bitcelle i SRAM modul.
WriteEnable og ReadEnable kan aldri være høy (1) samtidig. Ref modul ByteCell. */

module bitcell
    (
        input   inp,
        input   inpn,
        input   we,
        input   re,
        input   ren,
        output  outp
    );

    wire Q0;
    wire Q0n;
    wire Q1;
    wire Q1n;
    wire T0;
    wire T1;

    // supply rails. Logical 1
    supply1 VDD;
    supply0 GND;

    // D-latch
    nand(Q0, inp, we);
    nand(Q0n, inpn, we);
    nand(Q1, Q0, Q1n);
    nand(Q1n, Q0n, Q1);

    // Tri-state buffer
    pmos(T0, VDD, Q1n);
    nmos(T1, GND, Q1n);
    pmos(outp, T0, ren);
    nmos(outp, T1, re);
endmodule

verilog_mem8x8_m_tri_state_buffer/bytecell.v
/* 
Se vedlegg for kretskjema.
En bytecelle bestående av 8 stk bitceller med enkel logikk for kontroll av 
utgangsignalene WriteEnable og ReadEnable fra inngangsignalene sel(ect) og op(eration). .
Tar inn 8 bit inp(ut) signal og fordeler informasjonen til de tilhørende 8 bitcellene.
gir tilsvarende outp(ut) fra de 8 innbyrdes bitcellene.
Modul Bitcelle er konstruert i filen bitcelle.v
 */

`include "bitcell.v"                // include bitcell module to the script

module bytecell
    (
        input   [7:0]   inp,        // input
        input   [7:0]   inpn,       // input not
        input           op,         // operation, write = 1, read = 0
        input           sel,        // select. 1 if read/write operation is valid for one bytecell, else 0.
        output  [7:0]   outp        // output
    );

    wire re;                     // read enable
    wire ren;                    // read enable not
    wire we;                     // write enable
    wire opn;

    // F Block. Se vedlegg for kretskjema
    not(opn, op);                   // opn = ~op
    and(we, sel, op);               // we = sel & op
    nand(ren, sel, opn);            // ren = sel & ~op
    not(re, ren);                   // re = ~ren

    // 8 stk bitceller
    genvar i;   generate
        for(i = 0; i < 8; i = i + 1) begin : bitcell_insts_i
            bitcell bitcells
            (
                .inp    (inp[i]),
                .inpn   (inpn[i]),
                .we     (we),
                .re     (re),
                .ren    (ren),
                .outp   (outp[i])
            );
        end
    endgenerate
endmodule

verilog_mem8x8_m_tri_state_buffer/demux1to8bit.v
/* 
8 to 1 demux module
Se vedlegg for kretskjema 
*/
module demux1to8bit
    (
        input           inp,
        input   [2:0]   adr,
        output  [7:0]   outp
    );

    wire    [2:0]   not_adr;

    not(not_adr[0], adr[0]);
    not(not_adr[1], adr[1]);
    not(not_adr[2], adr[2]);

    and(outp[0],    inp,    not_adr[2],    not_adr[1],    not_adr[0]);
    and(outp[1],    inp,    not_adr[2],    not_adr[1],    adr[0]);
    and(outp[2],    inp,    not_adr[2],    adr[1],        not_adr[0]);
    and(outp[3],    inp,    not_adr[2],    adr[1],        adr[0]);
    and(outp[4],    inp,    adr[2],        not_adr[1],    not_adr[0]);
    and(outp[5],    inp,    adr[2],        not_adr[1],    adr[0]);
    and(outp[6],    inp,    adr[2],        adr[1],        not_adr[0]);
    and(outp[7],    inp,    adr[2],        adr[1],        adr[0]);

endmodule

verilog_mem8x8_m_tri_state_buffer/ram.v
`include "bytecell.v"               
`include "demux1to8bit.v"

module ram
    (
        input   [7:0]   inp,
        input   [2:0]   adr,
        input           op,
        input           sel,
        output  [7:0]   outp
    );

    wire    [7:0]   outp_demux;
    wire    [7:0]   inpn;

    // invert the input
    genvar j; generate
        for(j = 0; j < 8; j = j + 1) begin : inpn_insts1
            assign inpn[j] = ~inp[j];
        end
    endgenerate

    demux1to8bit demux1to8bit_inst1
    (
        .inp    (sel),
        .adr    (adr),
        .outp   (outp_demux)
    );

    // instantiate 8 bytecell modules
    genvar i; generate
        for (i = 0; i < 8; i = i + 1) begin : bytecell_insts1
            bytecell bytecell_inst (
                .inp    (inp),
                .inpn   (inpn),
                .op     (op),
                .sel    (outp_demux[i]),
                .outp   (outp)
            );
        end
    endgenerate
endmodule

verilog_mem8x8_m_tri_state_buffer/flipflop.v
module flipflop
    (
        input   inp,
        input   clk,
        output  outp
    );

    wire P0;
    wire P1;
    wire inpn;
    wire outpn;
    wire clkN;
    wire clkPE;

    not(clkN, clk);
    and(clkPE, clk, clkN);

    not(inpn, inp);
    nand(P0, inp, clkPE);
    nand(P1, inpn, clkPE);
    nand(outp, P0, outpn);
    nand(outpn, P1, outp);
endmodule

verilog_mem8x8_m_tri_state_buffer/FSM.v
`include "flipflop.v"

module fsm
    (
        input op,
        input sel,
        input clk,
        output valid,
        output rw
    );

    wire P0;
    wire P1;
    wire P2;
    wire P3;
    wire P4;
    

    and(P0, op, sel);
    or(P3, P0, P1);
    not(P1, P2);
    nand(P2, valid, rw);
    and(P4, P2, sel);


    flipflop ff1 (
        .inp(P4),
        .clk(clk),
        .outp(valid)
    );

    flipflop ff2 (
        .inp(P3),
        .clk(clk),
        .outp(rw)
    );
endmodule

verilog_mem8x8_m_tri_state_buffer/mem_system.v
`include "ram.v"
`include "FSM.v"

module mem_system
    (
        input clk,
        input [7:0] i,
        input [2:0] adr,
        input op, select,
        output [7:0] o
    );

    wire valid_connect;
    wire rw_connect;

    fsm fsm1 (
        .op(op),
        .sel(select),
        .clk(clk),
        .valid(valid_connect),
        .rw(rw_connect)
    );

    ram ram1 (
        .inp(i),
        .adr(adr),
        .op(rw_connect),
        .sel(valid_connect),
        .outp(o)
    );
endmodule

verilog_mem8x8_m_tri_state_buffer/mem_system_tb.v
`include "mem_system.v"

module mem_system_tb;

    reg clk;
    reg [7:0] i;
    reg [2:0] adr;
    reg op, select;
    wire [7:0] o;

    // Instantiate the Unit Under Test (UUT)
    mem_system mem_system1 (
        .clk(clk), 
        .i(i), 
        .adr(adr),
        .op(op), .select(select), 
        .o(o)
    );

    always begin
        #5 clk = 1;
        #5 clk = 0;
    end

    initial begin
        $dumpfile("mem_system_waveform.vcd");
        $dumpvars(1, mem_system_tb);

        clk = 0;
        i = 0;
        adr = 0;
        op = 0; select = 0;

        #25;
        //Write "LS SWK !" to memory
        op = 1; select = 1;
        adr = 3'b000; i = 8'b01001100; // ASCII 'L'
        #20 adr = 3'b001; i = 8'b01010011; // ASCII 'S'
        #20 adr = 3'b010; i = 8'b00100000; // ASCII space
        #20 adr = 3'b011; i = 8'b01010011; // ASCII 'S'
        #20 adr = 3'b100; i = 8'b01010111; // ASCII 'W'
        #20 adr = 3'b101; i = 8'b01001011; // ASCII 'K'
        #20 adr = 3'b110; i = 8'b00100000; // ASCII space
        #20 adr = 3'b111; i = 8'b00100001; // ASCII '!'
        #20;
        
        op = 0; select = 0; adr=3'b000; i = 8'b00000000;
        #30;

        //Read from memory
        #10 op = 0; select = 1; adr = 3'b000;
        #10 adr = 3'b001;
        #10 adr = 3'b010;
        #10 adr = 3'b011;
        #10 adr = 3'b100;
        #10 adr = 3'b101;
        #10 adr = 3'b110;
        #10 adr = 3'b111;

        #10 op = 0; select = 0; adr=3'b000;

        #100 $finish;
    end
    
endmodule

verilog_mem8x8_m_tri_state_buffer/mem_system_waveform.vcd
$date
	Mon Nov 04 09:55:38 2024
$end
$version
	Icarus Verilog
$end
$timescale
	1s
$end
$scope module mem_system_tb $end
$var wire 8 ! o [7:0] $end
$var reg 3 " adr [2:0] $end
$var reg 1 # clk $end
$var reg 8 $ i [7:0] $end
$var reg 1 % op $end
$var reg 1 & select $end
$upscope $end
$enddefinitions $end
$comment Show the parameter values. $end
$dumpall
$end
#0
$dumpvars
0&
0%
b0 $
0#
b0 "
bx !
$end
#5
bz !
1#
#10
0#
#15
1#
#20
0#
#25
1#
b1001100 $
1&
1%
#30
0#
#35
1#
#40
0#
#45
1#
b1010011 $
b1 "
#50
0#
#55
1#
#60
0#
#65
1#
b100000 $
b10 "
#70
0#
#75
1#
#80
0#
#85
1#
b1010011 $
b11 "
#90
0#
#95
1#
#100
0#
#105
1#
b1010111 $
b100 "
#110
0#
#115
1#
#120
0#
#125
1#
b1001011 $
b101 "
#130
0#
#135
1#
#140
0#
#145
1#
b100000 $
b110 "
#150
0#
#155
1#
#160
0#
#165
1#
b100001 $
b111 "
#170
0#
#175
1#
#180
0#
#185
1#
b0 $
b0 "
0&
0%
#190
0#
#195
1#
#200
0#
#205
1#
#210
0#
#215
1#
#220
0#
#225
b1001100 !
1#
1&
#230
0#
#235
b1010011 !
1#
b1 "
#240
0#
#245
b100000 !
1#
b10 "
#250
0#
#255
b1010011 !
1#
b11 "
#260
0#
#265
b1010111 !
1#
b100 "
#270
0#
#275
b1001011 !
1#
b101 "
#280
0#
#285
b100000 !
1#
b110 "
#290
0#
#295
b100001 !
1#
b111 "
#300
0#
#305
bz !
1#
b0 "
0&
