verilog_mem8x8_m_tri_state_buffer/bitcell.v
/* 
Se vedlegg for kretskjema
Enkel bitcelle i SRAM modul.
WriteEnable og ReadEnable kan aldri være høy (1) samtidig. Ref modul ByteCell. */

module bitcell
    (
        input   inp,
        input   inpn,
        input   we,
        input   re,
        input   ren,
        output  outp
    );

    wire Q0;
    wire Q0n;
    wire Q1;
    wire Q1n;
    wire T0;
    wire T1;

    // supply rails. Logical 1
    supply1 VDD;
    supply0 GND;

    // D-latch
    nand(Q0, inp, we);
    nand(Q0n, inpn, we);
    nand(Q1, Q0, Q1n);
    nand(Q1n, Q0n, Q1);

    // Tri-state buffer
    pmos(T0, VDD, Q1n);
    nmos(T1, GND, Q1n);
    pmos(outp, T0, ren);
    nmos(outp, T1, re);
endmodule

verilog_mem8x8_m_tri_state_buffer/bytecell.v
/* 
Se vedlegg for kretskjema.
En bytecelle bestående av 8 stk bitceller med enkel logikk for kontroll av 
utgangsignalene WriteEnable og ReadEnable fra inngangsignalene sel(ect) og op(eration). .
Tar inn 8 bit inp(ut) signal og fordeler informasjonen til de tilhørende 8 bitcellene.
gir tilsvarende outp(ut) fra de 8 innbyrdes bitcellene.
Modul Bitcelle er konstruert i filen bitcelle.v
 */

`include "bitcell.v"                // include bitcell module to the script

module bytecell
    (
        input   [7:0]   inp,        // input
        input   [7:0]   inpn,       // input not
        input           op,         // operation, write = 1, read = 0
        input           sel,        // select. 1 if read/write operation is valid for one bytecell, else 0.
        output  [7:0]   outp        // output
    );

    wire re;                     // read enable
    wire ren;                    // read enable not
    wire we;                     // write enable
    wire opn;

    // F Block. Se vedlegg for kretskjema
    not(opn, op);                   // opn = ~op
    and(we, sel, op);               // we = sel & op
    nand(ren, sel, opn);            // ren = sel & ~op
    not(re, ren);                   // re = ~ren

    // 8 stk bitceller
    genvar i;   generate
        for(i = 0; i < 8; i = i + 1) begin : bitcell_insts_i
            bitcell bitcells
            (
                .inp    (inp[i]),
                .inpn   (inpn[i]),
                .we     (we),
                .re     (re),
                .ren    (ren),
                .outp   (outp[i])
            );
        end
    endgenerate
endmodule

verilog_mem8x8/demux1to8bit.v
/* 
8 to 1 demux module
Se vedlegg for kretskjema 
*/
module demux1to8bit
    (
        input           inp,
        input   [2:0]   addr,
        output  [7:0]   outp
    );

    wire    [2:0]   not_addr;

    not(not_addr[0], addr[0]);
    not(not_addr[1], addr[1]);
    not(not_addr[2], addr[2]);

    and(outp[0],    inp,    not_addr[2],    not_addr[1],    not_addr[0]);
    and(outp[1],    inp,    not_addr[2],    not_addr[1],    addr[0]);
    and(outp[2],    inp,    not_addr[2],    addr[1],        not_addr[0]);
    and(outp[3],    inp,    not_addr[2],    addr[1],        addr[0]);
    and(outp[4],    inp,    addr[2],        not_addr[1],    not_addr[0]);
    and(outp[5],    inp,    addr[2],        not_addr[1],    addr[0]);
    and(outp[6],    inp,    addr[2],        addr[1],        not_addr[0]);
    and(outp[7],    inp,    addr[2],        addr[1],        addr[0]);

endmodule

verilog_mem8x8_m_tri_state_buffer/ram.v
/* 
8x8 bit SRAM modul
se vedlegg for kretskjema.
 */

// include the bytecell modules used for this project
`include "bytecell.v"               
`include "demux1to8bit.v"

module ram
    (
        input   [7:0]   inp,
        input   [2:0]   addr,
        input           op,
        input           sel,
        output  [7:0]   outp
    );

    wire    [7:0]   outp_demux;
    wire    [7:0]   inpn;


    // invert the input
    genvar j; generate
        for(j = 0; j < 8; j = j + 1) begin : inpn_insts1
            assign inpn[j] = ~inp[j];
        end
    endgenerate

    // instantiate the demux1to8bit module
    demux1to8bit demux1to8bit_inst1
    (
        .inp    (sel),
        .addr   (addr),
        .outp   (outp_demux)
    );

    // instantiate the 8 bytecell modules
    genvar i; generate
        for (i = 0; i < 8; i = i + 1) begin : bytecell_insts1
            bytecell bytecell_inst (
                .inp    (inp),
                .inpn   (inpn),
                .op     (op),
                .sel    (outp_demux[i]),
                .outp   (outp)
            );
        end
    endgenerate
endmodule

verilog_mem8x8_m_tri_state_buffer/ram_tb.v
`include "ram.v"                // include the module

// Test Bench for RAM modul
module ram_tb;
    reg     [7:0]   inp;
    reg     [2:0]   addr;
    reg             op;
    reg             sel;
    wire    [7:0]   outp;

    ram ram_inst1 (
        .inp    (inp),
        .addr   (addr),
        .op     (op),
        .sel    (sel),
        .outp   (outp)
    );

    initial begin
        $dumpfile("ram_waveform.vcd");
        $dumpvars(1, ram_tb);

        inp  = 8'b00000000;
        addr = 3'b000;
        op   = 1'b0;
        sel  = 1'b0;

                #10 sel <= 1'b1;    op <= 1'b1;     inp <= 8'b10101010;     addr <= 3'b001;         // write AA to address 1
        #10 sel <= 1'b0;
        #10 sel <= 1'b1;    op <= 1'b0;     addr <= 3'b001;                                 // read from address 1
        #10 sel <= 1'b0;
        #10 sel <= 1'b1;    op <= 1'b1;     inp <= 8'b11001100;     addr <= 3'b010;         // write CC to address 2
        #10 sel <= 1'b0;
        #10 sel <= 1'b1;    op <= 1'b0;     addr <= 3'b010;                                 // read from address 2
        #10 sel <= 1'b0;
        #10 sel <= 1'b1;    op <= 1'b1;     inp <= 8'b11110000;     addr <= 3'b011;         // write F0 to address 3
        #10 sel <= 1'b0;
        #10 sel <= 1'b1;    op <= 1'b0;     addr <= 3'b011;                                 // read from address 3
        #10 sel <= 1'b0;
        #10 sel <= 1'b1;    op <= 1'b1;     inp <= 8'b00001111;     addr <= 3'b100;         // write 0F to address 4
        #10 sel <= 1'b0;
        #10 sel <= 1'b1;    op <= 1'b0;     addr <= 3'b100;                                 // read from address 4
        #10 sel <= 1'b0;
        #10 sel <= 1'b1;    op <= 1'b1;     inp <= 8'b00110011;     addr <= 3'b101;         // write 33 to address 5
        #10 sel <= 1'b0;
        #10 sel <= 1'b1;    op <= 1'b0;     addr <= 3'b101;                                 // read from address 5
        #10 sel <= 1'b0;
        #10 sel <= 1'b1;    op <= 1'b1;     inp <= 8'b01010101;     addr <= 3'b110;         // write 55 to address 6
        #10 sel <= 1'b0;
        #10 sel <= 1'b1;    op <= 1'b0;     addr <= 3'b110;                                 // read from address 6
        #10 sel <= 1'b0;
        #10 sel <= 1'b1;    op <= 1'b1;     inp <= 8'b10011001;     addr <= 3'b111;         // write 99 to address 7
        #10 sel <= 1'b0;
        #10 sel <= 1'b1;    op <= 1'b0;     addr <= 3'b111;                                 // read from address 7
        #10 sel <= 1'b0;

        #10;

/*         #10 sel <= 1'b1;    op <= 1'b1;     inp <= 8'b10101010;     addr <= 3'b001;         // write AA to address 1
        #10 sel <= 1'b0;
        #10 sel <= 1'b1;    op <= 1'b0;     addr <= 3'b001;                                 // read from address 1
        #10 sel <= 1'b0;
        #10 sel <= 1'b1;    op <= 1'b0;     addr <= 3'b010;                                 // read from address 2
        #10 op  <= 1'b1;    inp <= 8'b10101011;                                             // write AB to address 2
        #10 op  <= 1'b0;
        #10 addr <= 3'b001;

        #10; */
    end
endmodule

verilog_mem8x8_m_tri_state_buffer/ram_waveform.vcd
$date
	Wed Oct 23 16:05:19 2024
$end
$version
	Icarus Verilog
$end
$timescale
	1s
$end
$scope module ram_tb $end
$var wire 8 ! outp [7:0] $end
$var reg 3 " addr [2:0] $end
$var reg 8 # inp [7:0] $end
$var reg 1 $ op $end
$var reg 1 % sel $end
$upscope $end
$enddefinitions $end
#0
$dumpvars
0%
0$
b0 #
b0 "
bz !
$end
#10
b1 "
b10101010 #
1$
1%
#20
0%
#30
b10101010 !
0$
1%
#40
bz !
0%
#50
b10 "
b11001100 #
1$
1%
#60
0%
#70
b11001100 !
0$
1%
#80
bz !
0%
#90
b11 "
b11110000 #
1$
1%
#100
0%
#110
b11110000 !
0$
1%
#120
bz !
0%
#130
b100 "
b1111 #
1$
1%
#140
0%
#150
b1111 !
0$
1%
#160
bz !
0%
#170
b101 "
b110011 #
1$
1%
#180
0%
#190
b110011 !
0$
1%
#200
bz !
0%
#210
b110 "
b1010101 #
1$
1%
#220
0%
#230
b1010101 !
0$
1%
#240
bz !
0%
#250
b111 "
b10011001 #
1$
1%
#260
0%
#270
b10011001 !
0$
1%
#280
bz !
0%
