verilog_mem8x8_latch/bitcell.v
/* 
Se vedlegg for kretskjema
Enkel bitcelle i SRAM modul.
WriteEnable og ReadEnable kan aldri være høy (1) samtidig. Ref modul ByteCell. */

module bitcell
    (
        input   inp,
        input   re,
        input   ren,
        input   we,
        input   wen,
        output  outp
    );

    wire Q0;
    wire Q1;
    wire Q2;



    pmos(Q0, inp, wen);
    nmos(Q0, inp, we);

    not(Q1, Q0);
    not(Q2, Q1);

    pmos(Q0, Q2, we);
    nmos(Q0, Q2, wen);

    pmos(outp, Q2, ren);
    nmos(outp, Q2, re);
endmodule

verilog_mem8x8/bitcell_tb.v
`include "bitcell.v"        // include the module

module bitcell_tb;
    reg     inp;
    reg     re;
    reg     we;
    reg     wen;
    reg     ren;
    wire    outp;

    bitcell bitcell_inst1
    (
        .inp    (inp),
        .we     (we),
        .re     (re),
        .outp   (outp),
        .wen    (wen),
        .ren    (ren)
    );

    initial begin
        $dumpfile("bitcell_waveform.vcd");
        $dumpvars(1, bitcell_tb);

        inp = 0;
        re  = 0;
        ren = 0;
        we  = 0;
        wen = 1;

        #5 re  <= 1; ren <= 0;
        #5 re  <= 0; ren <= 1;
        #5 inp <= 1; we <= 1; wen <= 0;
        #5 we  <= 0; wen <= 1;
        #5 inp <= 0;
        #5 re  <= 1; ren <= 0;
        #5 re  <= 0; we <= 1; ren <= 1; wen <= 0;
        #5 we  <= 0; wen <= 1;
        #5 re  <= 1; ren <= 0;
        #5 re  <= 0; ren <= 1;
        #5;
    end
endmodule

verilog_mem8x8_latch/bitcell_waveform.vcd
$date
	Mon Oct 21 08:44:31 2024
$end
$version
	Icarus Verilog
$end
$timescale
	1s
$end
$scope module bitcell_tb $end
$var wire 1 ! outp $end
$var reg 1 " inp $end
$var reg 1 # re $end
$var reg 1 $ ren $end
$var reg 1 % we $end
$var reg 1 & wen $end
$upscope $end
$enddefinitions $end
$comment Show the parameter values. $end
$dumpall
$end
#0
$dumpvars
1&
0%
0$
0#
0"
x!
$end
#5
1#
#10
z!
1$
0#
#15
0&
1%
1"
#20
1&
0%
#25
0"
#30
0$
1!
1#
#35
0&
z!
1$
1%
0#
#40
1&
0%
#45
0$
0!
1#
#50
z!
1$
0#
