verilog_mem8x8_latch/bitcell.v
/* 
Se vedlegg for kretskjema
Enkel bitcelle i SRAM modul.
WriteEnable og ReadEnable kan aldri være høy (1) samtidig. Ref modul ByteCell. */

module bitcell
    (
        input   inp,
        input   re,
        input   ren,
        input   we,
        input   wen,
        output  outp
    );

    wire Q0;
    wire Q1;
    wire Q2;



    pmos(Q0, inp, wen);
    nmos(Q0, inp, we);

    not(Q1, Q0);
    not(Q2, Q1);

    pmos(Q0, Q2, we);
    nmos(Q0, Q2, wen);

    pmos(outp, Q2, ren);
    nmos(outp, Q2, re);
endmodule

verilog_mem8x8_flippety_flop/bytecell.v
/* 
Se vedlegg for kretskjema.
En bytecelle bestående av 8 stk bitceller med enkel logikk for kontroll av 
utgangsignalene WriteEnable og ReadEnable fra inngangsignalene sel(ect) og op(eration). .
Tar inn 8 bit inp(ut) signal og fordeler informasjonen til de tilhørende 8 bitcellene.
gir tilsvarende outp(ut) fra de 8 innbyrdes bitcellene.
Modul Bitcelle er konstruert i filen bitcelle.v
 */

`include "bitcell.v"                // include bitcell module to the script

cd module bytecell
    (
        input   [7:0]   inp,        // input
        input           op,         // operation, write = 1, read = 0
        input           sel,        // select. 1 if read/write operation is valid for one bytecell, else 0.
        output  [7:0]   outp        // output
    );
    wire    re;                     // read enable
    wire    we;                     // write enable
    

    and(we, sel, op);               // we = sel & op
    and(re, sel, ~op);              // re = sel & ~op


    bitcell bitcells [7:0]          // 8xbitcell
    (
        .inp(inp),
        .re(re),
        .we(we),
        .outp(outp)
    );
endmodule

verilog_mem8x8/demux1to8bit.v
/* 
8 to 1 demux module
Se vedlegg for kretskjema 
*/
module demux1to8bit
    (
        input           inp,
        input   [2:0]   addr,
        output  [7:0]   outp
    );

    wire    [2:0]   not_addr;

    not(not_addr[0], addr[0]);
    not(not_addr[1], addr[1]);
    not(not_addr[2], addr[2]);

    and(outp[0],    inp,    not_addr[2],    not_addr[1],    not_addr[0]);
    and(outp[1],    inp,    not_addr[2],    not_addr[1],    addr[0]);
    and(outp[2],    inp,    not_addr[2],    addr[1],        not_addr[0]);
    and(outp[3],    inp,    not_addr[2],    addr[1],        addr[0]);
    and(outp[4],    inp,    addr[2],        not_addr[1],    not_addr[0]);
    and(outp[5],    inp,    addr[2],        not_addr[1],    addr[0]);
    and(outp[6],    inp,    addr[2],        addr[1],        not_addr[0]);
    and(outp[7],    inp,    addr[2],        addr[1],        addr[0]);

endmodule

verilog_mem8x8_latch/ram.v
/* 
8x8 bit SRAM modul
se vedlegg for kretskjema.
 */

// include the bytecell modules used for this project
`include "bytecell.v"               
`include "demux1to8bit.v"

module ram
    (
        input   [7:0]   inp,
        input   [2:0]   addr,
        input           op,
        input           sel,
        output  [7:0]   outp
    );

    wire    [7:0]   outp_demux;

    demux1to8bit demux1to8bit_inst1
    (
        .inp    (sel),
        .addr   (addr),
        .outp   (outp_demux)
    );

    genvar i; generate
        for (i = 0; i < 8; i = i + 1) begin : bytecell_insts1
            bytecell bytecell_inst (
                .inp    (inp),
                .op     (op),
                .sel    (outp_demux[i]),
                .outp   (outp)
            );
        end
    endgenerate

endmodule

verilog_mem8x8_latch/ram_tb.v
`include "ram.v"                // include the module

// Test Bench for RAM modul
module ram_tb;
    reg     [7:0]   inp;
    reg     [2:0]   addr;
    reg             op;
    reg             sel;
    wire    [7:0]   outp;

    ram ram_inst1 (
        .inp    (inp),
        .addr   (addr),
        .op     (op),
        .sel    (sel),
        .outp   (outp)
    );

    initial begin
        $dumpfile("ram_waveform.vcd");
        $dumpvars(1, ram_tb);

        inp  = 8'b00000000;
        addr = 3'b000;
        op   = 1'b0;
        sel  = 1'b0;

        #10 sel <= 1'b1;    op <= 1'b1;     inp <= 8'b10101010;     addr <= 3'b001;         // write AA to address 1
        #10 sel <= 1'b0;
        #10 sel <= 1'b1;    op <= 1'b0;     addr <= 3'b001;                                 // read from address 1
        #10 sel <= 1'b0;
        #10 sel <= 1'b1;    op <= 1'b0;     addr <= 3'b010;                                 // read from address 2
        #10 op  <= 1'b1;    inp <= 8'b10101011;                                             // write AB to address 2
        #10 op  <= 1'b0;
        #10;
    end
endmodule

verilog_mem8x8_latch/ram_waveform.vcd
$date
	Mon Oct 21 08:50:55 2024
$end
$version
	Icarus Verilog
$end
$timescale
	1s
$end
$scope module ram_tb $end
$var wire 8 ! outp [7:0] $end
$var reg 3 " addr [2:0] $end
$var reg 8 # inp [7:0] $end
$var reg 1 $ op $end
$var reg 1 % sel $end
$upscope $end
$enddefinitions $end
$comment Show the parameter values. $end
$dumpall
$end
#0
$dumpvars
0%
0$
b0 #
b0 "
bz !
$end
#10
b1 "
b10101010 #
1$
1%
#20
0%
#30
b10101010 !
0$
1%
#40
bz !
0%
#50
bx !
b10 "
1%
#60
bz !
b10101011 #
1$
#70
b10101011 !
0$
